[
    {
        "time": "01 Mar 2018 12:48pm",
        "version": "cf6c1e72-6d0f-4644-8e74-3ac1058d897b",
        "deployed": "success"
    },
    {
        "time": "26 Feb 2018, 07:26:01 am",
        "version": "3ac1058d897b-cf6c1e72-6d0f-4644-8e74-",
        "deployed": "failed"
    },
    {
        "time": "25 Feb 2018, 12:05:11 pm",
        "version": "6d0f-cf6c1e72-4644-8e74-3ac1058d897b",
        "deployed": "success"
    },
    {
        "time": "23 Feb 2018, 07:26:01 am",
        "version": "4644-cf6c1e72-6d0f-4644-8e74-3ac1058d897b",
        "deployed": "success"
    },
    {
        "time": "19 Feb 2018, 12:05:11 pm",
        "version": "8e74-6d0f-4644-sdsd-3ac1058d897b",
        "deployed": "failed"
    }
]